axographio/__init__.py
axographio/extension.cp39-win_amd64.pyd
axographio/version.py
axographio/include/axograph_readwrite/AxoGraph Digitized File
axographio/include/axograph_readwrite/AxoGraph Graph File
axographio/include/axograph_readwrite/AxoGraph X File.axgx
axographio/tests/__init__.py
axographio/tests/test_axographio.py
axographio-0.3.2.dist-info/LICENSE
axographio-0.3.2.dist-info/METADATA
axographio-0.3.2.dist-info/WHEEL
axographio-0.3.2.dist-info/top_level.txt
axographio-0.3.2.dist-info/RECORD
