Metadata-Version: 2.1
Name: axographio
Version: 0.3.2
Summary: A Python package for reading and writing AxoGraph data files
Home-page: https://github.com/CWRUChielLab/axographio
Author: Kendrick Shaw, Jeffrey Gill
Author-email: kms15@case.edu, jeffrey.p.gill@gmail.com
Maintainer: Jeffrey Gill
Maintainer-email: jeffrey.p.gill@gmail.com
License: BSD License
Keywords: physiology,electrophysiology,axograph
Platform: UNKNOWN
Classifier: Programming Language :: Python
Classifier: Programming Language :: Python :: 2
Classifier: Programming Language :: Python :: 3
Classifier: Development Status :: 4 - Beta
Classifier: Intended Audience :: Developers
Classifier: Intended Audience :: Science/Research
Classifier: License :: OSI Approved :: BSD License
Classifier: Topic :: Scientific/Engineering :: Bio-Informatics
Requires-Dist: numpy
